kingsoftcloud_sdk_python-1.5.8.43.dist-info/licenses/LICENSE
ksyun/__init__.py
ksyun/client/__init__.py
ksyun/client/actiontrail/__init__.py
ksyun/client/actiontrail/v20190401/__init__.py
ksyun/client/actiontrail/v20190401/client.py
ksyun/client/actiontrail/v20190401/models.py
ksyun/client/aicp/__init__.py
ksyun/client/aicp/v20240612/__init__.py
ksyun/client/aicp/v20240612/client.py
ksyun/client/aicp/v20240612/models.py
ksyun/client/aicp/v20251212/__init__.py
ksyun/client/aicp/v20251212/client.py
ksyun/client/aicp/v20251212/models.py
ksyun/client/bill/__init__.py
ksyun/client/bill/v20180601/__init__.py
ksyun/client/bill/v20180601/client.py
ksyun/client/bill/v20180601/models.py
ksyun/client/bill/v20220601/__init__.py
ksyun/client/bill/v20220601/client.py
ksyun/client/bill/v20220601/models.py
ksyun/client/bill_union/__init__.py
ksyun/client/bill_union/v20200101/__init__.py
ksyun/client/bill_union/v20200101/client.py
ksyun/client/bill_union/v20200101/models.py
ksyun/client/bill_union/v20221222/__init__.py
ksyun/client/bill_union/v20221222/client.py
ksyun/client/bill_union/v20221222/models.py
ksyun/client/bill_union/v20250801/__init__.py
ksyun/client/bill_union/v20250801/client.py
ksyun/client/bill_union/v20250801/models.py
ksyun/client/bws/__init__.py
ksyun/client/bws/v20160304/__init__.py
ksyun/client/bws/v20160304/client.py
ksyun/client/bws/v20160304/models.py
ksyun/client/cdn/__init__.py
ksyun/client/cdn/v20160901/__init__.py
ksyun/client/cdn/v20160901/client.py
ksyun/client/cdn/v20160901/models.py
ksyun/client/cdn/v20200630/__init__.py
ksyun/client/cdn/v20200630/client.py
ksyun/client/cdn/v20200630/models.py
ksyun/client/cdn/v20200901/__init__.py
ksyun/client/cdn/v20200901/client.py
ksyun/client/cdn/v20200901/models.py
ksyun/client/cdn/v20211201/__init__.py
ksyun/client/cdn/v20211201/client.py
ksyun/client/cdn/v20211201/models.py
ksyun/client/cdn/v3/__init__.py
ksyun/client/cdn/v3/client.py
ksyun/client/cdn/v3/models.py
ksyun/client/cen/__init__.py
ksyun/client/cen/v20160304/__init__.py
ksyun/client/cen/v20160304/client.py
kingsoftcloud_sdk_python-1.5.8.43.dist-info/METADATA
kingsoftcloud_sdk_python-1.5.8.43.dist-info/WHEEL
kingsoftcloud_sdk_python-1.5.8.43.dist-info/top_level.txt
kingsoftcloud_sdk_python-1.5.8.43.dist-info/RECORD
