Metadata-Version: 2.4
Name: kingsoftcloud-sdk-python
Version: 1.5.8.43
Summary: Kingsoft Cloud SDK for Python
Home-page: https://github.com/ksyun/ksyun-sdk-python
Author: Kingsoft Cloud
Maintainer-email: fengyikai@kingsoft.com
License: Apache License 2.0
Platform: any
Classifier: Development Status :: 5 - Production/Stable
Classifier: Intended Audience :: Developers
Classifier: License :: OSI Approved :: Apache Software License
Classifier: Programming Language :: Python
Classifier: Programming Language :: Python :: 2.7
Classifier: Programming Language :: Python :: 3
Classifier: Programming Language :: Python :: 3.6
Classifier: Programming Language :: Python :: 3.7
Classifier: Programming Language :: Python :: 3.8
Classifier: Programming Language :: Python :: 3.9
Classifier: Programming Language :: Python :: 3.10
License-File: LICENSE
Requires-Dist: requests<3.0.0,>=2.20.0
Requires-Dist: requests-aws4auth<2.0.0,>=1.0.1
Requires-Dist: six
Dynamic: author
Dynamic: classifier
Dynamic: description
Dynamic: home-page
Dynamic: license
Dynamic: license-file
Dynamic: maintainer-email
Dynamic: platform
Dynamic: requires-dist
Dynamic: summary
